icar/__init__.py
icar/collections.py
icar/enums.py
icar/geojson.py
icar/resources.py
icar/types.py
icar_pydantic-1.4.0.dev2.dist-info/licenses/LICENSE
icar_pydantic-1.4.0.dev2.dist-info/METADATA
icar_pydantic-1.4.0.dev2.dist-info/WHEEL
icar_pydantic-1.4.0.dev2.dist-info/top_level.txt
icar_pydantic-1.4.0.dev2.dist-info/RECORD
