Metadata-Version: 2.4
Name: ICAR-pydantic
Version: 1.4.0.dev2
Summary: ICAR Pydantic models
Author-email: Jules Robichaud-Gagnon <j.robichaudg+pypi@gmail.com>
License: MIT
Project-URL: homepage, https://github.com/adewg/ICAR-pydantic
Project-URL: repository, https://github.com/adewg/ICAR-pydantic
Project-URL: tracker, https://github.com/adewg/ICAR-pydantic/issues
Classifier: Programming Language :: Python :: 3
Classifier: Programming Language :: Python :: 3 :: Only
Classifier: Programming Language :: Python :: 3.10
Classifier: Programming Language :: Python :: 3.11
Classifier: Programming Language :: Python :: 3.12
Classifier: Programming Language :: Python :: 3.13
Classifier: License :: OSI Approved :: MIT License
Classifier: Operating System :: OS Independent
Requires-Python: >=3.10
License-File: LICENSE
Requires-Dist: pydantic>=2.0.0
Dynamic: license-file
